ena_upload/__init__.py
ena_upload/config.toml
ena_upload-0.1.0.dist-info/entry_points.txt
ena_upload-0.1.0.dist-info/LICENSE
ena_upload-0.1.0.dist-info/WHEEL
ena_upload-0.1.0.dist-info/METADATA
ena_upload-0.1.0.dist-info/RECORD
